liuml-0.1.1.dist-info/METADATA
liuml-0.1.1.dist-info/WHEEL
liuml-0.1.1.dist-info/entry_points.txt
lml/__init__.py
lml/cli.py
lml/commands/__init__.py
lml/commands/docker.py
lml/commands/huggingface.py
lml/commands/pip.py
lml/common/__init__.py
lml/common/logger.py
lml/common/path.py
lml/common/profile.py
lml/common/register.py
lml/common/runner.py
lml/common/singleton.py
lml/common/string.py
lml/image/__init__.py
lml/image/opencv.py
lml/japanese/__init__.py
lml/japanese/japanese.py
lml/openai/RateLimiter.py
lml/openai/__init__.py
lml/torch/__init__.py
lml/torch/exts/__init__.py
lml/torch/exts/yolov5_ext/__init__.py
lml/torch/exts/yolov5_ext/postprogress.py
lml/torch/networks/__init__.py
lml/torch/networks/c3net.py
lml/torch/ops/__init__.py
lml/torch/ops/conv.py
lml/torch/utils/__init__.py
lml/torch/utils/cryptor.py
lml/vector/__init__.py
lml/vector/db.py
liuml-0.1.1.dist-info/RECORD
